turkish_tokenizer-1.0.1.dist-info/METADATA
turkish_tokenizer-1.0.1.dist-info/WHEEL
turkish_tokenizer/__init__.py
turkish_tokenizer/turkish_tokenizer.cpython-313-darwin.so
turkish_tokenizer-1.0.1.dist-info/RECORD
