Metadata-Version: 2.4
Name: turkish-tokenizer
Version: 1.0.1
Classifier: Programming Language :: Rust
Classifier: Programming Language :: Python :: Implementation :: CPython
Classifier: Programming Language :: Python :: Implementation :: PyPy
Summary: A high-performance Turkish tokenizer based on linguistic rules and BPE, written in Rust.
Requires-Python: >=3.8
